xprompt/__init__.py
xprompt/admin_client.py
xprompt/client_prompt_parser.py
xprompt/client_services/__init__.py
xprompt/client_services/dummy_parser.py
xprompt/client_services/llamahub_connectors/__init__.py
xprompt/client_services/llamahub_connectors/google_docs.py
xprompt/constants.py
xprompt/data_client.py
xprompt/openai_client.py
xprompt/schemas.py
xprompt/utils.py
xprompt_client-0.1.4.dist-info/METADATA
xprompt_client-0.1.4.dist-info/WHEEL
xprompt_client-0.1.4.dist-info/RECORD
