Metadata-Version: 2.1
Name: xprompt-client
Version: 0.1.4
Summary: 
Author: Yi Lu
Author-email: yilu331@gmail.com
Requires-Python: >=3.10,<4.0
Classifier: Programming Language :: Python :: 3
Classifier: Programming Language :: Python :: 3.10
Classifier: Programming Language :: Python :: 3.11
Provides-Extra: llama-index
Requires-Dist: llama-index (==0.8.26.post1) ; extra == "llama-index"
Requires-Dist: requests (>=2.31.0,<3.0.0)
Requires-Dist: typer (>=0.9.0,<0.10.0)
Requires-Dist: xprompt-common (==0.1.5)
